LICENSE
scoach/__init__.py
scoach/cli/__init__.py
scoach/cli/run.py
scoach/cli/script.py
scoach/cli/utils.py
scoach/constants.py
scoach/data.py
scoach/executor.py
scoach/logging.py
scoach/models.py
scoach/scheduler.py
scoach/scoach.py
scoach/settings/__init__.py
scoach/settings/base.py
scoach/settings/dev.py
scoach/settings/prod.py
scoach/utils.py
scoach-0.1.9.dist-info/entry_points.txt
scoach-0.1.9.dist-info/LICENSE
scoach-0.1.9.dist-info/WHEEL
scoach-0.1.9.dist-info/METADATA
scoach-0.1.9.dist-info/RECORD
