Metadata-Version: 2.1
Name: scoach
Version: 0.1.9
Summary: Setup for training Tensorflow models on SLURM clusters.
Home-page: https://github.com/gabriel-milan/scoach
License: GPL-3.0
Keywords: tensorflow,machine learning,hpc,slurm
Author: Gabriel Gazola Milan
Author-email: gabriel.gazola@poli.ufrj.br
Requires-Python: >=3.8,<4.0
Classifier: Development Status :: 4 - Beta
Classifier: Intended Audience :: Developers
Classifier: License :: OSI Approved :: GNU General Public License v3 (GPLv3)
Classifier: Programming Language :: Python :: 3
Classifier: Programming Language :: Python :: 3.10
Classifier: Programming Language :: Python :: 3.8
Classifier: Programming Language :: Python :: 3.9
Classifier: Topic :: Software Development :: Libraries :: Python Modules
Requires-Dist: Django (>=3.2.0,<4.0.0)
Requires-Dist: Jinja2 (>=3.0.0,<4.0.0)
Requires-Dist: PyYAML (>=5.4.0,<6.0.0)
Requires-Dist: dask_jobqueue (>=0.7.0,<0.8.0)
Requires-Dist: importlib-metadata (>=1.0,<2.0); python_version < "3.8"
Requires-Dist: loguru (>=0.5.0,<0.6.0)
Requires-Dist: minio (>=7.0.0,<8.0.0)
Requires-Dist: prefect (>=0.15.0,<0.16.0)
Requires-Dist: psycopg2-binary (>=2.9.0,<3.0.0)
Requires-Dist: tensorflow (>=2.0.0,<3.0.0)
Requires-Dist: typer (>=0.4.0,<0.5.0)
Project-URL: Repository, https://github.com/gabriel-milan/scoach
